{
"id": 1633,
    "name": "Poralmaster",
    "author": "Axolotl299",
    "creators": [],
    "verifier": "Axolotl299",
    "verification": "",
    "percentToQualify": 100,
    "password": "Free to copy",
    "records": [
                        {
"user": "hedshot",
"link": "https://www.youtube.com/watch?v=Kawi_1mS9U0",
"percent": 100,
"hz": "240"
},
{
"user": "Scattered"
"link": "https://youtu.be/w6PHGWXjgpA?si=7-QjshBDQgkmJa6_"
"percent": 100
"hz": "240"
},
      {
"user": "LuhFrosted",
"link": "https://youtu.be/-WE-4bcxDdM",
"percent": 100,
"hz": "165"
}
    ]
}
